gdp_time_series/__init__.py
gdp_time_series/__main__.py
gdp_time_series/pipeline_registry.py
gdp_time_series/settings.py
gdp_time_series/pipelines/__init__.py
gdp_time_series/pipelines/feature_pipeline/__init__.py
gdp_time_series/pipelines/feature_pipeline/auxiliary_functions.py
gdp_time_series/pipelines/feature_pipeline/data_extraction.py
gdp_time_series/pipelines/feature_pipeline/ft_store_functions.py
gdp_time_series/pipelines/feature_pipeline/groups.py
gdp_time_series/pipelines/feature_pipeline/nodes.py
gdp_time_series/pipelines/feature_pipeline/pipeline.py
gdp_time_series/pipelines/feature_pipeline/settings.py
gdp_time_series/pipelines/feature_pipeline/utils.py
gdp_time_series/pipelines/prediction_pipeline/__init__.py
gdp_time_series/pipelines/prediction_pipeline/nodes.py
gdp_time_series/pipelines/prediction_pipeline/pipeline.py
gdp_time_series/pipelines/prediction_pipeline/settings.py
gdp_time_series/pipelines/prediction_pipeline/utils.py
gdp_time_series/pipelines/training_pipeline/__init__.py
gdp_time_series/pipelines/training_pipeline/auxiliary_functions.py
gdp_time_series/pipelines/training_pipeline/nodes.py
gdp_time_series/pipelines/training_pipeline/pipeline.py
gdp_time_series/pipelines/training_pipeline/settings.py
gdp_time_series/pipelines/training_pipeline/utils.py
tests/pipelines/__init__.py
gdp_time_series-0.2.dist-info/METADATA
gdp_time_series-0.2.dist-info/WHEEL
gdp_time_series-0.2.dist-info/entry_points.txt
gdp_time_series-0.2.dist-info/top_level.txt
gdp_time_series-0.2.dist-info/RECORD
