Metadata-Version: 2.1
Name: gdp-time-series
Version: 0.2
Requires-Dist: adagio ==0.2.4
Requires-Dist: aiohttp ==3.8.6
Requires-Dist: aiosignal ==1.3.1
Requires-Dist: alembic ==1.12.0
Requires-Dist: altair ==4.2.2
Requires-Dist: antlr4-python3-runtime ==4.11.1
Requires-Dist: anyconfig ==0.10.1
Requires-Dist: anyio ==3.7.1
Requires-Dist: appdirs ==1.4.4
Requires-Dist: argon2-cffi ==23.1.0
Requires-Dist: argon2-cffi-bindings ==21.2.0
Requires-Dist: arrow ==1.3.0
Requires-Dist: async-timeout ==4.0.3
Requires-Dist: attrs ==23.1.0
Requires-Dist: avro ==1.11.0
Requires-Dist: Babel ==2.13.0
Requires-Dist: backcall ==0.2.0
Requires-Dist: backports.zoneinfo ==0.2.1
Requires-Dist: beautifulsoup4 ==4.12.2
Requires-Dist: binaryornot ==0.4.4
Requires-Dist: black ==22.12.0
Requires-Dist: bleach ==6.1.0
Requires-Dist: blinker ==1.6.3
Requires-Dist: blosc ==1.11.1
Requires-Dist: blosc2 ==2.0.0
Requires-Dist: boto3 ==1.28.62
Requires-Dist: botocore ==1.31.62
Requires-Dist: build ==0.10.0
Requires-Dist: CacheControl ==0.13.1
Requires-Dist: cachetools ==4.2.4
Requires-Dist: certifi ==2023.7.22
Requires-Dist: cffi ==1.16.0
Requires-Dist: chardet ==5.2.0
Requires-Dist: charset-normalizer ==3.3.0
Requires-Dist: cleo ==2.0.1
Requires-Dist: click ==8.1.7
Requires-Dist: cloudpickle ==2.2.1
Requires-Dist: colorama ==0.4.6
Requires-Dist: comm ==0.1.4
Requires-Dist: commonmark ==0.9.1
Requires-Dist: confluent-kafka ==1.9.0
Requires-Dist: contourpy ==1.1.1
Requires-Dist: cookiecutter ==2.4.0
Requires-Dist: coverage ==7.3.2
Requires-Dist: crashtest ==0.4.1
Requires-Dist: cryptography ==41.0.4
Requires-Dist: cycler ==0.12.1
Requires-Dist: Cython ==3.0.3
Requires-Dist: darts ==0.26.0
Requires-Dist: databricks-cli ==0.18.0
Requires-Dist: dataclasses ==0.6
Requires-Dist: db-dtypes ==1.1.1
Requires-Dist: debugpy ==1.8.0
Requires-Dist: decorator ==5.1.1
Requires-Dist: defusedxml ==0.7.1
Requires-Dist: dill ==0.3.7
Requires-Dist: distlib ==0.3.7
Requires-Dist: docker ==5.0.3
Requires-Dist: dulwich ==0.21.6
Requires-Dist: dynaconf ==3.2.3
Requires-Dist: entrypoints ==0.4
Requires-Dist: et-xmlfile ==1.1.0
Requires-Dist: exceptiongroup ==1.1.3
Requires-Dist: fastavro ==1.8.2
Requires-Dist: fastjsonschema ==2.18.1
Requires-Dist: filelock ==3.12.4
Requires-Dist: flake8 ==4.0.1
Requires-Dist: Flask ==2.0.0
Requires-Dist: fonttools ==4.43.1
Requires-Dist: frozenlist ==1.4.0
Requires-Dist: fs ==2.4.16
Requires-Dist: fsspec ==2022.11.0
Requires-Dist: fugue ==0.8.6
Requires-Dist: fugue-sql-antlr ==0.1.7
Requires-Dist: furl ==2.1.3
Requires-Dist: future ==0.18.3
Requires-Dist: gitdb ==4.0.10
Requires-Dist: GitPython ==3.1.37
Requires-Dist: google-api-core ==2.12.0
Requires-Dist: google-auth ==2.23.2
Requires-Dist: google-auth-oauthlib ==1.1.0
Requires-Dist: google-cloud-bigquery ==3.12.0
Requires-Dist: google-cloud-bigquery-storage ==2.22.0
Requires-Dist: google-cloud-core ==2.3.3
Requires-Dist: google-crc32c ==1.5.0
Requires-Dist: google-resumable-media ==2.6.0
Requires-Dist: googleapis-common-protos ==1.60.0
Requires-Dist: great-expectations ==0.14.13
Requires-Dist: greenlet ==3.0.0
Requires-Dist: grpcio ==1.59.0
Requires-Dist: grpcio-status ==1.59.0
Requires-Dist: gunicorn ==20.1.0
Requires-Dist: hampel ==1.0.2
Requires-Dist: holidays ==0.34
Requires-Dist: hopsworks ==3.2.0
Requires-Dist: hsfs ==3.2.1
Requires-Dist: hsml ==3.2.1
Requires-Dist: idna ==3.4
Requires-Dist: importlib-metadata ==4.13.0
Requires-Dist: importlib-resources ==6.1.0
Requires-Dist: iniconfig ==2.0.0
Requires-Dist: installer ==0.7.0
Requires-Dist: ipykernel ==6.25.2
Requires-Dist: ipython ==7.34.0
Requires-Dist: ipython-genutils ==0.2.0
Requires-Dist: ipywidgets ==8.1.1
Requires-Dist: isort ==5.12.0
Requires-Dist: itsdangerous ==2.1.2
Requires-Dist: jaraco.classes ==3.3.0
Requires-Dist: javaobj-py3 ==0.4.3
Requires-Dist: jedi ==0.19.1
Requires-Dist: jeepney ==0.8.0
Requires-Dist: Jinja2 ==3.0.3
Requires-Dist: jmespath ==0.10.0
Requires-Dist: joblib ==1.3.2
Requires-Dist: json5 ==0.9.14
Requires-Dist: jsonpatch ==1.33
Requires-Dist: jsonpointer ==2.4
Requires-Dist: jsonschema ==4.17.3
Requires-Dist: jsonschema-specifications ==2023.7.1
Requires-Dist: jupyter ==1.0.0
Requires-Dist: jupyter-console ==6.6.3
Requires-Dist: jupyter-server ==1.24.0
Requires-Dist: jupyter-client ==7.4.9
Requires-Dist: jupyter-core ==5.3.2
Requires-Dist: jupyterlab ==3.5.3
Requires-Dist: jupyterlab-pygments ==0.2.2
Requires-Dist: jupyterlab-widgets ==3.0.9
Requires-Dist: jupyterlab-server ==2.15.2
Requires-Dist: kedro ==0.18.4
Requires-Dist: kedro-telemetry ==0.2.5
Requires-Dist: keyring ==24.2.0
Requires-Dist: kiwisolver ==1.4.5
Requires-Dist: lightgbm ==4.1.0
Requires-Dist: lightning-utilities ==0.9.0
Requires-Dist: llvmlite ==0.41.0
Requires-Dist: lxml ==4.9.3
Requires-Dist: Mako ==1.2.4
Requires-Dist: Markdown ==3.5
Requires-Dist: MarkupSafe ==2.0.1
Requires-Dist: matplotlib ==3.7.3
Requires-Dist: matplotlib-inline ==0.1.6
Requires-Dist: mccabe ==0.6.1
Requires-Dist: miceforest ==5.6.3
Requires-Dist: mistune ==3.0.2
Requires-Dist: mlflow ==2.1.1
Requires-Dist: mock ==5.1.0
Requires-Dist: more-itertools ==10.1.0
Requires-Dist: mpmath ==1.3.0
Requires-Dist: msgpack ==1.0.7
Requires-Dist: multidict ==6.0.4
Requires-Dist: mypy-extensions ==1.0.0
Requires-Dist: nbclassic ==1.0.0
Requires-Dist: nbclient ==0.8.0
Requires-Dist: nbconvert ==7.9.2
Requires-Dist: nbformat ==5.9.2
Requires-Dist: nbstripout ==0.6.1
Requires-Dist: nest-asyncio ==1.5.8
Requires-Dist: networkx ==3.1
Requires-Dist: nfoursid ==1.0.1
Requires-Dist: notebook ==6.5.6
Requires-Dist: notebook-shim ==0.2.3
Requires-Dist: numba ==0.58.0
Requires-Dist: numexpr ==2.8.6
Requires-Dist: numpy ==1.24.4
Requires-Dist: nvidia-cublas-cu12 ==12.1.3.1
Requires-Dist: nvidia-cuda-cupti-cu12 ==12.1.105
Requires-Dist: nvidia-cuda-nvrtc-cu12 ==12.1.105
Requires-Dist: nvidia-cuda-runtime-cu12 ==12.1.105
Requires-Dist: nvidia-cudnn-cu12 ==8.9.2.26
Requires-Dist: nvidia-cufft-cu12 ==11.0.2.54
Requires-Dist: nvidia-curand-cu12 ==10.3.2.106
Requires-Dist: nvidia-cusolver-cu12 ==11.4.5.107
Requires-Dist: nvidia-cusparse-cu12 ==12.1.0.106
Requires-Dist: nvidia-nccl-cu12 ==2.18.1
Requires-Dist: nvidia-nvjitlink-cu12 ==12.2.140
Requires-Dist: nvidia-nvtx-cu12 ==12.1.105
Requires-Dist: oauthlib ==3.2.2
Requires-Dist: openpyxl ==3.1.2
Requires-Dist: orderedmultidict ==1.0.1
Requires-Dist: packaging ==22.0
Requires-Dist: pandas ==1.5.3
Requires-Dist: pandas-gbq ==0.17.9
Requires-Dist: pandocfilters ==1.5.0
Requires-Dist: parso ==0.8.3
Requires-Dist: pathspec ==0.11.2
Requires-Dist: patsy ==0.5.3
Requires-Dist: pexpect ==4.8.0
Requires-Dist: pickleshare ==0.7.5
Requires-Dist: Pillow ==10.0.1
Requires-Dist: pip-tools ==6.14.0
Requires-Dist: pkginfo ==1.9.6
Requires-Dist: pkgutil-resolve-name ==1.3.10
Requires-Dist: platformdirs ==3.11.0
Requires-Dist: pluggy ==1.0.0
Requires-Dist: pmdarima ==2.0.3
Requires-Dist: poetry ==1.6.1
Requires-Dist: poetry-core ==1.7.0
Requires-Dist: poetry-plugin-export ==1.5.0
Requires-Dist: polars ==0.19.8
Requires-Dist: prometheus-client ==0.17.1
Requires-Dist: prometheus-flask-exporter ==0.22.4
Requires-Dist: prompt-toolkit ==3.0.39
Requires-Dist: proto-plus ==1.22.3
Requires-Dist: protobuf ==4.24.4
Requires-Dist: psutil ==5.9.5
Requires-Dist: psycopg2 ==2.9.3
Requires-Dist: psycopg2-binary ==2.9.9
Requires-Dist: ptyprocess ==0.7.0
Requires-Dist: py ==1.11.0
Requires-Dist: py-cpuinfo ==9.0.0
Requires-Dist: pyarrow ==6.0.1
Requires-Dist: pyasn1 ==0.5.0
Requires-Dist: pyasn1-modules ==0.3.0
Requires-Dist: pycodestyle ==2.8.0
Requires-Dist: pycparser ==2.21
Requires-Dist: pycryptodomex ==3.19.0
Requires-Dist: pydata-google-auth ==1.8.2
Requires-Dist: pyflakes ==2.4.0
Requires-Dist: Pygments ==2.16.1
Requires-Dist: PyHopsHive ==0.6.4.1.dev0
Requires-Dist: pyhumps ==1.6.1
Requires-Dist: pyjks ==20.0.0
Requires-Dist: PyJWT ==2.8.0
Requires-Dist: PyMySQL ==1.1.0
Requires-Dist: pyod ==1.1.0
Requires-Dist: pyparsing ==2.4.7
Requires-Dist: pyproject-hooks ==1.0.0
Requires-Dist: pyrsistent ==0.19.3
Requires-Dist: pytest ==6.2.5
Requires-Dist: pytest-cov ==3.0.0
Requires-Dist: pytest-mock ==1.13.0
Requires-Dist: python-dateutil ==2.8.2
Requires-Dist: python-dotenv ==1.0.0
Requires-Dist: python-slugify ==8.0.1
Requires-Dist: pytoolconfig ==1.2.5
Requires-Dist: pytorch-lightning ==2.0.9.post0
Requires-Dist: pytz ==2022.7.1
Requires-Dist: PyYAML ==6.0.1
Requires-Dist: pyzmq ==24.0.1
Requires-Dist: qpd ==0.4.4
Requires-Dist: qtconsole ==5.4.4
Requires-Dist: QtPy ==2.4.0
Requires-Dist: querystring-parser ==1.2.4
Requires-Dist: rapidfuzz ==2.15.2
Requires-Dist: referencing ==0.30.2
Requires-Dist: requests ==2.31.0
Requires-Dist: requests-oauthlib ==1.3.1
Requires-Dist: requests-toolbelt ==1.0.0
Requires-Dist: rich ==12.6.0
Requires-Dist: rope ==1.5.1
Requires-Dist: rpds-py ==0.10.4
Requires-Dist: rsa ==4.9
Requires-Dist: ruamel.yaml ==0.17.17
Requires-Dist: ruamel.yaml.clib ==0.2.8
Requires-Dist: s3transfer ==0.7.0
Requires-Dist: scikit-learn ==1.3.1
Requires-Dist: scipy ==1.10.1
Requires-Dist: SecretStorage ==3.3.3
Requires-Dist: Send2Trash ==1.8.2
Requires-Dist: shap ==0.43.0
Requires-Dist: shellingham ==1.5.3
Requires-Dist: six ==1.16.0
Requires-Dist: slicer ==0.0.7
Requires-Dist: smmap ==5.0.1
Requires-Dist: sniffio ==1.3.0
Requires-Dist: soupsieve ==2.5
Requires-Dist: SQLAlchemy ==1.4.49
Requires-Dist: sqlglot ==18.12.0
Requires-Dist: sqlparse ==0.4.4
Requires-Dist: statsforecast ==1.6.0
Requires-Dist: statsmodels ==0.14.0
Requires-Dist: sympy ==1.12
Requires-Dist: tables ==3.8.0
Requires-Dist: tabulate ==0.9.0
Requires-Dist: tbats ==1.1.3
Requires-Dist: tensorboardX ==2.6.2.2
Requires-Dist: termcolor ==2.3.0
Requires-Dist: terminado ==0.17.1
Requires-Dist: text-unidecode ==1.3
Requires-Dist: threadpoolctl ==3.2.0
Requires-Dist: thrift ==0.16.0
Requires-Dist: tinycss2 ==1.2.1
Requires-Dist: toml ==0.10.2
Requires-Dist: tomli ==2.0.1
Requires-Dist: tomlkit ==0.12.1
Requires-Dist: toolz ==0.12.0
Requires-Dist: toposort ==1.10
Requires-Dist: torch ==2.1.0
Requires-Dist: torchmetrics ==1.2.0
Requires-Dist: tornado ==6.3.3
Requires-Dist: tqdm ==4.66.1
Requires-Dist: traitlets ==5.11.2
Requires-Dist: triad ==0.9.1
Requires-Dist: triton ==2.1.0
Requires-Dist: trove-classifiers ==2023.10.17
Requires-Dist: twofish ==0.3.0
Requires-Dist: types-python-dateutil ==2.8.19.14
Requires-Dist: typing-extensions ==4.8.0
Requires-Dist: tzlocal ==5.1
Requires-Dist: urllib3 ==1.26.17
Requires-Dist: virtualenv ==20.24.5
Requires-Dist: wcwidth ==0.2.8
Requires-Dist: webencodings ==0.5.1
Requires-Dist: websocket-client ==1.6.4
Requires-Dist: Werkzeug ==2.0.0
Requires-Dist: widgetsnbextension ==4.0.9
Requires-Dist: xarray ==2023.1.0
Requires-Dist: xgboost ==2.0.0
Requires-Dist: yarl ==1.9.2
Requires-Dist: zipp ==3.17.0
Provides-Extra: docs
Requires-Dist: docutils <0.18.0 ; extra == 'docs'
Requires-Dist: sphinx ~=3.4.3 ; extra == 'docs'
Requires-Dist: sphinx-rtd-theme ==0.5.1 ; extra == 'docs'
Requires-Dist: nbsphinx ==0.8.1 ; extra == 'docs'
Requires-Dist: nbstripout ~=0.4 ; extra == 'docs'
Requires-Dist: sphinx-autodoc-typehints ==1.11.1 ; extra == 'docs'
Requires-Dist: sphinx-copybutton ==0.3.1 ; extra == 'docs'
Requires-Dist: ipykernel <7.0,>=5.3 ; extra == 'docs'
Requires-Dist: Jinja2 <3.1.0 ; extra == 'docs'
Requires-Dist: myst-parser ~=0.17.2 ; extra == 'docs'
